pyqtcolor/__init__.py
pyqtcolor/test.py
pyqtcolor-2.9.dist-info/METADATA
pyqtcolor-2.9.dist-info/WHEEL
pyqtcolor-2.9.dist-info/top_level.txt
pyqtcolor-2.9.dist-info/RECORD
