Metadata-Version: 2.1
Name: pyqtcolor
Version: 2.9
Summary: Bring Colorful Code
Author-email: smithshwan@gmail.com
License: Eclipse Public License 2.0
